tests/__init__.py
tests/argguard_test.py
yamlattributes/__init__.py
yamlattributes/yamlattributes.py
yamlattributes-0.2.0.dist-info/LICENSE
yamlattributes-0.2.0.dist-info/METADATA
yamlattributes-0.2.0.dist-info/WHEEL
yamlattributes-0.2.0.dist-info/top_level.txt
yamlattributes-0.2.0.dist-info/RECORD
