Metadata-Version: 2.1
Name: yamlattributes
Version: 0.2.0
Summary: Utility class to assign YAML file entries to class attributes
Home-page: https://github.com/gcascio/yaml-attributes
Author: Giovanni Cascio
Author-email: giovanni@maternavis.com
License: UNKNOWN
Platform: UNKNOWN
Classifier: Programming Language :: Python :: 3
Classifier: License :: OSI Approved :: MIT License
Classifier: Operating System :: OS Independent
Requires-Python: >=3.7
License-File: LICENSE
